hockey.v
module hockey(

input clk,
input rst,

input BTN_A,
input BTN_B,

input [1:0] DIR_A,
input [1:0] DIR_B,

input [2:0] Y_in_A,
input [2:0] Y_in_B,

/*output reg LEDA,
output reg LEDB,
output reg [4:0] LEDX,

output reg [6:0] SSD7,
output reg [6:0] SSD6,
output reg [6:0] SSD5,
output reg [6:0] SSD4, 
output reg [6:0] SSD3,
output reg [6:0] SSD2,
output reg [6:0] SSD1,
output reg [6:0] SSD0   */

output reg [2:0] X_COORD,
output reg [2:0] Y_COORD


);

reg turn;
reg [7:0] timer;
reg [1:0] dirY;
reg [2:0] scoreA;
reg [2:0] scoreB;

reg [3:0] cState;

parameter [3:0] IDLE = 4'b0000;
parameter [3:0] DISP = 4'b0001;
parameter [3:0] HIT_A = 4'b0010;
parameter [3:0] HIT_B = 4'b0011;
parameter [3:0] SEND_A = 4'b0100;
parameter [3:0] SEND_B = 4'b0101;
parameter [3:0] RESP_A = 4'b0110;
parameter [3:0] RESP_B = 4'b0111;
parameter [3:0] GOAL_A = 4'b1000;
parameter [3:0] GOAL_B = 4'b1001;
parameter [3:0] GAME_OVER = 4'b1010;

parameter [2:0] TWO_SECS = 3'd4;

always @(posedge clk or posedge rst)
begin
    if (rst) begin
        timer <= 0;
        dirY <= 0;
        scoreA <= 0;
        scoreB <= 0;
        X_COORD <= 0;
        Y_COORD <= 0;
        cState <= IDLE;
    end
    else 
    begin
        case (cState)
            IDLE:
            begin
                if (BTN_A == 0 && BTN_B == 1) 
                begin
                    turn <= 1;
                    cState <= DISP;
                end
                else if (BTN_A == 1 && BTN_B == 0) 
                begin
                    turn <= 0;
                    cState <= DISP;
                end
                else 
                begin
                    cState <= IDLE;
                end
            end
            DISP:
            begin
                if (timer < TWO_SECS) 
                begin
                    timer <= timer + 1;
                    cState <= DISP;
                end
                else 
                begin
                    timer <= 0;
                    if (turn == 1) 
                    begin
                        cState <= HIT_B;
                    end
                    else 
                    begin
                        cState <= HIT_A;
                    end
                end
            end
            HIT_A:
            begin
                if (BTN_A && (Y_in_A < 5))
                begin
                    X_COORD <= 0;
                    Y_COORD <= Y_in_A;
                    dirY <= DIR_A;
                    cState <= SEND_B;
                end
                else
                begin
                    cState <= HIT_A;
                end
            end
            HIT_B:
            begin
                if (BTN_B && (Y_in_B < 5))
                begin
                    X_COORD <= 4;
                    Y_COORD <= Y_in_B;
                    dirY <= DIR_B;
                    cState <= SEND_A;
                end
                else
                begin
                    cState <= HIT_B;
                end
            end
            SEND_A:
            begin
                if (timer < TWO_SECS) 
                begin
                    timer <= timer + 1;
                    cState <= SEND_A;
                end
                else
                begin
                    timer <= 0;
                    case (dirY)
                    2'b00:
                        if (X_COORD > 1)
                        begin
                            X_COORD <= X_COORD - 1;
                            cState <= SEND_A;
                        end
                        else
                        begin
                            X_COORD <= 0;
                            cState <= RESP_A;
                        end
                    2'b01:
                    begin
                        if (Y_COORD == 4)
                        begin
                            dirY <= 2'b10;
                            Y_COORD <= Y_COORD - 1;
                            if (X_COORD > 1)
                            begin
                                X_COORD <= X_COORD - 1;
                                cState <= SEND_A;
                            end
                            else
                            begin
                                X_COORD <= 0;
                                cState <= RESP_A;
                            end
                        end
                        else 
                        begin
                            Y_COORD <= Y_COORD + 1;
                            if (X_COORD > 1)
                            begin
                                X_COORD <= X_COORD - 1;
                                cState <= SEND_A;
                            end
                            else
                            begin
                                X_COORD <= 0;
                                cState <= RESP_A;
                            end
                        end
                    end
                    2'b10:
                    begin
                        if (Y_COORD == 0)
                        begin
                            dirY <= 2'b01;
                            Y_COORD <= Y_COORD + 1;
                            if (X_COORD > 1)
                            begin
                                X_COORD <= X_COORD - 1;
                                cState <= SEND_A;
                            end
                            else
                            begin
                                X_COORD <= 0;
                                cState <= RESP_A;
                            end
                        end
                        else 
                        begin
                            Y_COORD <= Y_COORD - 1;
                            if (X_COORD > 1)
                            begin
                                X_COORD <= X_COORD - 1;
                                cState <= SEND_A;
                            end
                            else
                            begin
                                X_COORD <= 0;
                                cState <= RESP_A;
                            end
                        end
                    end
                    default:
                    begin
                        cState <= SEND_A;
                    end
                    endcase
                end
            end
            SEND_B:
            begin
                if (timer < TWO_SECS) 
                begin
                    timer <= timer + 1;
                    cState <= SEND_B;
                end
                else
                begin
                    timer <= 0;
                    case (dirY)
                    2'b00:
                        if (X_COORD < 3)
                        begin
                            X_COORD <= X_COORD + 1;
                            cState <= SEND_B;
                        end
                        else
                        begin
                            X_COORD <= 4;
                            cState <= RESP_B;
                        end
                    2'b01:
                    begin
                        if (Y_COORD == 4)
                        begin
                            dirY <= 2'b10;
                            Y_COORD <= Y_COORD - 1;
                            if (X_COORD < 3)
                            begin
                                X_COORD <= X_COORD + 1;
                                cState <= SEND_B;
                            end
                            else
                            begin
                                X_COORD <= 4;
                                cState <= RESP_B;
                            end
                        end
                        else 
                        begin
                            Y_COORD <= Y_COORD + 1;
                            if (X_COORD < 3)
                            begin
                                X_COORD <= X_COORD + 1;
                                cState <= SEND_B;
                            end
                            else
                            begin
                                X_COORD <= 4;
                                cState <= RESP_B;
                            end
                        end
                    end
                    2'b10:
                    begin
                        if (Y_COORD == 0)
                        begin
                            dirY <= 2'b01;
                            Y_COORD <= Y_COORD + 1;
                            if (X_COORD < 3)
                            begin
                                X_COORD <= X_COORD + 1;
                                cState <= SEND_B;
                            end
                            else
                            begin
                                X_COORD <= 4;
                                cState <= RESP_B;
                            end
                        end
                        else 
                        begin
                            Y_COORD <= Y_COORD - 1;
                            if (X_COORD < 3)
                            begin
                                X_COORD <= X_COORD + 1;
                                cState <= SEND_B;
                            end
                            else
                            begin
                                X_COORD <= 4;
                                cState <= RESP_B;
                            end
                        end
                    end
                    default:
                    begin
                        cState <= SEND_B;
                    end
                    endcase
                end
            end
            RESP_A:
            begin
                if (timer < TWO_SECS) 
                begin
                    if (BTN_A && (Y_COORD == Y_in_A))
                    begin
                        X_COORD <= 1;
                        timer <= 0;
                        case (DIR_A)
                            2'b00:
                            begin
                                dirY <= DIR_A;
                                cState <= SEND_B;
                            end
                            2'b01:
                            begin
                                if (Y_COORD == 4)
                                begin
                                    dirY <= 2'b10;
                                    Y_COORD <= Y_COORD - 1;
                                    cState <= SEND_B;
                                end
                                else
                                begin
                                    dirY <= DIR_A;
                                    Y_COORD <= Y_COORD + 1;
                                    cState <= SEND_B;
                                end
                            end
                            2'b10:
                            begin
                                if (Y_COORD == 0)
                                begin
                                    dirY <= 2'b01;
                                    Y_COORD <= Y_COORD + 1;
                                    cState <= SEND_B;
                                end
                                else
                                begin
                                    dirY <= DIR_A;
                                    Y_COORD <= Y_COORD - 1;
                                    cState <= SEND_B;
                                end
                            end
                            default:
                            begin
                                cState <= RESP_A;
                            end
                        endcase
                    end
                    else 
                    begin
                        timer <= timer + 1;
                        cState <= RESP_A;
                    end
                end
                else
                begin
                    timer <= 0;
                    scoreB <= scoreB + 1;
                    cState <= GOAL_B;
                end
            end
            RESP_B:
            begin
                if (timer < TWO_SECS) 
                begin
                    if (BTN_B && (Y_COORD == Y_in_B))
                    begin
                        X_COORD <= 3;
                        timer <= 0;
                        case (DIR_B)
                            2'b00:
                            begin
                                dirY <= DIR_B;
                                cState <= SEND_A;
                            end
                            2'b01:
                            begin
                                if (Y_COORD == 4)
                                begin
                                    dirY <= 2'b10;
                                    Y_COORD <= Y_COORD - 1;
                                    cState <= SEND_A;
                                end
                                else
                                begin
                                    dirY <= DIR_B;
                                    Y_COORD <= Y_COORD + 1;
                                    cState <= SEND_A;
                                end
                            end
                            2'b10:
                            begin
                                if (Y_COORD == 0)
                                begin
                                    dirY <= 2'b01;
                                    Y_COORD <= Y_COORD + 1;
                                    cState <= SEND_A;
                                end
                                else
                                begin
                                    dirY <= DIR_B;
                                    Y_COORD <= Y_COORD - 1;
                                    cState <= SEND_A;
                                end
                            end
                            default:
                            begin
                                cState <= RESP_B;
                            end
                        endcase
                    end
                    else 
                    begin
                        timer <= timer + 1;
                        cState <= RESP_B;
                    end
                end
                else
                begin
                    timer <= 0;
                    scoreA <= scoreA + 1;
                    cState <= GOAL_A;
                end
            end
            GOAL_A:
            begin
                if (timer < TWO_SECS) 
                begin
                    timer <= timer + 1;
                    cState <= GOAL_A;
                end
                else
                begin
                    timer <= 0;
                    if (scoreA == 3)
                    begin
                        turn <= 0;
                        cState <= GAME_OVER;
                    end
                    else
                    begin
                        cState <= HIT_B;
                    end
                end
            end
            GOAL_B:
            begin
                if (timer < TWO_SECS) 
                begin
                    timer <= timer + 1;
                    cState <= GOAL_B;
                end
                else
                begin
                    timer <= 0;
                    if (scoreB == 3)
                    begin
                        turn <= 1;
                        cState <= GAME_OVER;
                    end
                    else
                    begin
                        cState <= HIT_A;
                    end
                end
            end
            GAME_OVER:
            begin
                cState <= GAME_OVER;
            end
            default:
            begin
                cState <= IDLE;
            end
        endcase
    end
end

endmodule

hockey_tb.v
module hockey_tb();


parameter HP = 5;       // Half period of our clock signal
parameter FP = (2*HP);  // Full period of our clock signal

reg clk, rst, BTN_A, BTN_B;
reg [1:0] DIR_A;
reg [1:0] DIR_B;
reg [2:0] Y_in_A;
reg [2:0] Y_in_B;

wire [2:0] X_COORD, Y_COORD;

// Our design-under-test is the DigiHockey module
hockey dut(clk, rst, BTN_A, BTN_B, DIR_A, DIR_B, Y_in_A, Y_in_B, X_COORD,Y_COORD);

// This always statement automatically cycles between clock high and clock low in HP (Half Period) time. Makes writing test-benches easier.
always #HP clk = ~clk;

initial begin
    $dumpfile("hockey.vcd"); //  * Our waveform is saved under this file.
    $dumpvars(0,hockey_tb); // * Get the variables from the module.
    $display("Simulation started.");

	// Initialize variables
	clk = 0; 
    rst = 0;
    BTN_A = 0;
	BTN_B = 0;
	DIR_A = 0;
	DIR_B = 0;
    Y_in_A = 0;
    Y_in_B = 0;
    

	// Test 1
	// Reset 
	rst = 1;
	#FP;
	rst = 0;
	#FP;

	// Player A starts the game
	BTN_A = 1; 
	#FP;
	BTN_A = 0;
	#(4*FP);

	// HIT_A state, take inputs Y_IN_A and DIR_A
	Y_in_A = 2;
	DIR_A = 0;
	#FP;

	// Pressing BTN_A go to SEND_B state
	BTN_A = 1; 
	#FP;
	BTN_A = 0;

	// Take inputs Y_IN_B and BTN_B, Y_IN_B not equal to Puck's current Y position, go to GOAL_A state
	#(20*FP);
	Y_in_B = 3; 
	#FP;
	BTN_B = 1;
    #(2*FP); 
	BTN_B = 0;
	#(2*FP);

	// GOAL_A state, score (1-0)
	#(5*FP);
	
	// HIT_B state, Take inputs Y_IN_B and BTN_B 
	Y_in_B = 1;
	DIR_B = 1;
	#FP;

	// Pressing BTN_B go to SEND_A state
	BTN_B = 1; 
	#FP;
	BTN_B = 0;

	// Take inputs Y_IN_A and BTN_A, Y_IN_A equal to Puck's Y position, go to SEND_B state
	#(20*FP);
	Y_in_A = 3; 
	#FP;
	BTN_A = 1;
	#FP; 
	BTN_A = 0;
	
	// Take inputs Y_IN_B and BTN_B, Y_IN_B equal to Puck's Y position, go to SEND_A state
	#(15*FP);
	Y_in_B = 3;
	#FP; 
	BTN_B = 1;
	#FP; 
	BTN_B = 0;

	// Take inputs Y_IN_A and BTN_A, Y_IN_A not equal to Puck's Y position, go to GOAL_B state
	#(15*FP);
	Y_in_A = 2;
	#FP;
	BTN_A = 1;
	#(2*FP); 
	BTN_A = 0;
	#(2*FP); 
	
	// GOAL_B state, score (1-1)
	#(5*FP); 

	// HIT_A state, take inputs Y_IN_A and DIR_A
	Y_in_A = 2;
	DIR_A = 2;
	#FP;

	// Pressing BTN_A go to SEND_B state
	BTN_A = 1; 
	#FP;
	BTN_A = 0;

	// Take inputs Y_IN_B and BTN_B, Y_IN_B not equal to Puck's current Y position
	#(20*FP);
	Y_in_B = 3; 
	#FP;
	BTN_B = 1;
    #(2*FP); 
	BTN_B = 0;
	#(2*FP);

	// GOAL_A state, score (2-1)
	#(5*FP); 

	// HIT_B state, Take inputs Y_IN_B and BTN_B 
	Y_in_B = 3;
	DIR_B = 0;
	#FP;

	// Pressing BTN_B go to SEND_A state
	BTN_B = 1; 
	#FP;
	BTN_B = 0;

	// Take inputs Y_IN_A and BTN_A, Y_IN_A equal to Puck's Y position, go to SEND_B state
	#(20*FP);
	Y_in_A = 3; 
	#FP;
	BTN_A = 1;
	#FP; 
	BTN_A = 0;

	// Take inputs Y_IN_B and BTN_B, Y_IN_B equal to Puck's Y position, go to SEND_A state
	#(15*FP);
	Y_in_B = 1;
	#FP;
	BTN_B = 1;
	#FP; 
	BTN_B = 0;

	// Take inputs Y_IN_A and BTN_A, Y_IN_A equal to Puck's Y position, go to SEND_B state
	#(15*FP);
	Y_in_A = 1; 
	#FP;
	BTN_A = 1;
	#FP; 
	BTN_A = 0;

	// Take inputs Y_IN_B and BTN_B, Y_IN_B not equal to Puck's Y position, go to GOAL_A state
	#(15*FP);
	Y_in_B = 0;
	#FP;
	BTN_B = 1;
	#(2*FP); 
	BTN_B = 0;
	#(2*FP); 

	// GOAL_A state, score (3-1), game over
	#(5*FP);
	
	// Test 2
	BTN_A = 0;
	BTN_B = 0;
	DIR_A = 0;
	DIR_B = 0;
    Y_in_A = 0;
    Y_in_B = 0;
	// Reset 
	rst = 1;
	#FP;
	rst = 0;
	#FP;

	// Player B starts the game
	BTN_B = 1; 
	#FP;
	BTN_B = 0;
	#(4*FP);

	// HIT_B state, Take inputs Y_IN_B and BTN_B
	Y_in_B = 4;
	DIR_B = 2;
	#FP;

	// Pressing BTN_B go to SEND_A state
	BTN_B = 1; 
	#FP
	BTN_B = 0;

	// Take inputs Y_IN_A and BTN_A, Y_IN_A equal to Puck's current Y position, go to SEND_B state
	#(20*FP);
	Y_in_A = 0; 
	#FP;
	BTN_A = 1;
    #FP; 
	BTN_A = 0;

	// Take inputs Y_IN_B and BTN_B, Y_IN_B not equal to Puck's Y position, go to GOAL_A state
	#(15*FP);
	Y_in_B = 4;
	#FP;
	BTN_B = 1;
	#(2*FP); 
	BTN_B = 0;
	#(2*FP); 

	// GOAL_A state, score (1-0)
	#(5*FP);
	
	// HIT_B state, Take inputs Y_IN_B and BTN_B 
	Y_in_B = 1;
	DIR_B = 0;
	#FP;

	// Pressing BTN_B go to SEND_A state
	BTN_B = 1; 
	#FP;
	BTN_B = 0;

	// Take inputs Y_IN_A and BTN_A, Y_IN_A not equal to Puck's Y position, go to GOAL_B state
	#(20*FP);
	Y_in_A = 4; 
	#FP;
	BTN_A = 1;
	#(2*FP); 
	BTN_A = 0;
	#(2*FP); 
	
	// GOAL_B state, score (1-1)
	#(5*FP); 

	// HIT_A state, take inputs Y_IN_A and DIR_A
	Y_in_A = 2;
	DIR_A = 1;
	#FP;

	// Pressing BTN_A go to SEND_B state
	BTN_A = 1; 
	#FP;
	BTN_A = 0;

	// Take inputs Y_IN_B and BTN_B, Y_IN_B equal to Puck's Y position, go to SEND_A state
	#(20*FP);
	Y_in_B = 2; 
	#FP;
	BTN_B = 1;
    #FP; 
	BTN_B = 0;

	// Take inputs Y_IN_A and BTN_A, Y_IN_A equal to Puck's Y position, go to SEND_B state
	#(15*FP);
	Y_in_A = 0; 
	#FP;
	BTN_A = 1;
    #(2*FP); 
	BTN_A = 0;
	#(2*FP);

	// GOAL_B state, score (1-2)
	#(5*FP); 

	// HIT_A state, take inputs Y_IN_A and DIR_A 
	Y_in_A = 3;
	DIR_A = 0;
	#FP;

	// Pressing BTN_B go to SEND_A state
	BTN_A = 1; 
	#FP;
	BTN_A = 0;

	// Take inputs Y_IN_B and BTN_B, Y_IN_B equal to Puck's Y position, go to SEND_B state
	#(20*FP);
	Y_in_B = 3;
	DIR_B = 2; 
	#FP;
	BTN_B = 1;
	#FP; 
	BTN_B = 0;

	// Take inputs Y_IN_A and BTN_A, Y_IN_A equal to Puck's Y position, go to SEND_B state
	#(15*FP);
	Y_in_A = 1; 
	DIR_A = 1;
	#FP;
	BTN_A = 1;
	#FP; 
	BTN_A = 0;

	// Take inputs Y_IN_B and BTN_B, Y_IN_B equal to Puck's Y position, go to SEND_A state
	#(15*FP);
	Y_in_B = 3;
	#FP;
	BTN_B = 1;
	#FP; 
	BTN_B = 0;

	// Take inputs Y_IN_A and BTN_A, Y_IN_A equal to Puck's Y position, go to GOAL_B state
	#(15*FP);
	Y_in_A = 0; 
	#FP;
	BTN_A = 1;
	#(2*FP); 
	BTN_A = 0;
	#(2*FP);

	// GOAL_B state, score (1-3), game over
	#(5*FP);

    $display("Simulation finished.");
    $finish(); // Finish simulation.
end



endmodule

hockey.vcd
$date
	Tue Jan  2 15:22:56 2024
$end
$version
	Icarus Verilog
$end
$timescale
	1s
$end
$scope module hockey_tb $end
$var wire 3 ! Y_COORD [2:0] $end
$var wire 3 " X_COORD [2:0] $end
$var parameter 64 # FP $end
$var parameter 32 $ HP $end
$var reg 1 % BTN_A $end
$var reg 1 & BTN_B $end
$var reg 2 ' DIR_A [1:0] $end
$var reg 2 ( DIR_B [1:0] $end
$var reg 3 ) Y_in_A [2:0] $end
$var reg 3 * Y_in_B [2:0] $end
$var reg 1 + clk $end
$var reg 1 , rst $end
$scope module dut $end
$var wire 1 % BTN_A $end
$var wire 1 & BTN_B $end
$var wire 2 - DIR_A [1:0] $end
$var wire 2 . DIR_B [1:0] $end
$var wire 3 / Y_in_A [2:0] $end
$var wire 3 0 Y_in_B [2:0] $end
$var wire 1 + clk $end
$var wire 1 , rst $end
$var parameter 4 1 DISP $end
$var parameter 4 2 GAME_OVER $end
$var parameter 4 3 GOAL_A $end
$var parameter 4 4 GOAL_B $end
$var parameter 4 5 HIT_A $end
$var parameter 4 6 HIT_B $end
$var parameter 4 7 IDLE $end
$var parameter 4 8 RESP_A $end
$var parameter 4 9 RESP_B $end
$var parameter 4 : SEND_A $end
$var parameter 4 ; SEND_B $end
$var parameter 3 < TWO_SECS $end
$var reg 3 = X_COORD [2:0] $end
$var reg 3 > Y_COORD [2:0] $end
$var reg 4 ? cState [3:0] $end
$var reg 2 @ dirY [1:0] $end
$var reg 3 A scoreA [2:0] $end
$var reg 3 B scoreB [2:0] $end
$var reg 8 C timer [7:0] $end
$var reg 1 D turn $end
$upscope $end
$upscope $end
$enddefinitions $end
$comment Show the parameter values. $end
$dumpall
b100 <
b101 ;
b100 :
b111 9
b110 8
b0 7
b11 6
b10 5
b1001 4
b1000 3
b1010 2
b1 1
b101 $
b1010 #
$end
#0
$dumpvars
xD
b0 C
b0 B
b0 A
b0 @
b0 ?
b0 >
b0 =
b0 0
b0 /
b0 .
b0 -
1,
0+
b0 *
b0 )
b0 (
b0 '
0&
0%
b0 "
b0 !
$end
#5
1+
#10
0+
0,
#15
1+
#20
0+
1%
#25
b1 ?
0D
1+
#30
0+
0%
#35
b1 C
1+
#40
0+
#45
b10 C
1+
#50
0+
#55
b11 C
1+
#60
0+
#65
b100 C
1+
#70
0+
b10 )
b10 /
#75
b10 ?
b0 C
1+
#80
0+
1%
#85
b101 ?
b10 !
b10 >
1+
#90
0+
0%
#95
b1 C
1+
#100
0+
#105
b10 C
1+
#110
0+
#115
b11 C
1+
#120
0+
#125
b100 C
1+
#130
0+
#135
b1 "
b1 =
b0 C
1+
#140
0+
#145
b1 C
1+
#150
0+
#155
b10 C
1+
#160
0+
#165
b11 C
1+
#170
0+
#175
b100 C
1+
#180
0+
#185
b10 "
b10 =
b0 C
1+
#190
0+
#195
b1 C
1+
#200
0+
#205
b10 C
1+
#210
0+
#215
b11 C
1+
#220
0+
#225
b100 C
1+
#230
0+
#235
b11 "
b11 =
b0 C
1+
#240
0+
#245
b1 C
1+
#250
0+
#255
b10 C
1+
#260
0+
#265
b11 C
1+
#270
0+
#275
b100 C
1+
#280
0+
#285
b111 ?
b100 "
b100 =
b0 C
1+
#290
0+
b11 *
b11 0
#295
b1 C
1+
#300
0+
1&
#305
b10 C
1+
#310
0+
#315
b11 C
1+
#320
0+
0&
#325
b100 C
1+
#330
0+
#335
b1000 ?
b1 A
b0 C
1+
#340
0+
#345
b1 C
1+
#350
0+
#355
b10 C
1+
#360
0+
#365
b11 C
1+
#370
0+
#375
b100 C
1+
#380
0+
#385
b11 ?
b0 C
1+
#390
0+
b1 (
b1 .
b1 *
b1 0
#395
1+
#400
0+
1&
#405
b100 ?
b1 @
b1 !
b1 >
1+
#410
0+
0&
#415
b1 C
1+
#420
0+
#425
b10 C
1+
#430
0+
#435
b11 C
1+
#440
0+
#445
b100 C
1+
#450
0+
#455
b11 "
b11 =
b10 !
b10 >
b0 C
1+
#460
0+
#465
b1 C
1+
#470
0+
#475
b10 C
1+
#480
0+
#485
b11 C
1+
#490
0+
#495
b100 C
1+
#500
0+
#505
b10 "
b10 =
b11 !
b11 >
b0 C
1+
#510
0+
#515
b1 C
1+
#520
0+
#525
b10 C
1+
#530
0+
#535
b11 C
1+
#540
0+
#545
b100 C
1+
#550
0+
#555
b1 "
b1 =
b100 !
b100 >
b0 C
1+
#560
0+
#565
b1 C
1+
#570
0+
#575
b10 C
1+
#580
0+
#585
b11 C
1+
#590
0+
#595
b100 C
1+
#600
0+
#605
b110 ?
b0 "
b0 =
b11 !
b11 >
b10 @
b0 C
1+
#610
0+
b11 )
b11 /
#615
b1 C
1+
#620
0+
1%
#625
b101 ?
b0 @
b0 C
b1 "
b1 =
1+
#630
0+
0%
#635
b1 C
1+
#640
0+
#645
b10 C
1+
#650
0+
#655
b11 C
1+
#660
0+
#665
b100 C
1+
#670
0+
#675
b10 "
b10 =
b0 C
1+
#680
0+
#685
b1 C
1+
#690
0+
#695
b10 C
1+
#700
0+
#705
b11 C
1+
#710
0+
#715
b100 C
1+
#720
0+
#725
b11 "
b11 =
b0 C
1+
#730
0+
#735
b1 C
1+
#740
0+
#745
b10 C
1+
#750
0+
#755
b11 C
1+
#760
0+
#765
b100 C
1+
#770
0+
#775
b111 ?
b100 "
b100 =
b0 C
1+
#780
0+
b11 *
b11 0
#785
b1 C
1+
#790
0+
1&
#795
b100 ?
b100 !
b100 >
b1 @
b0 C
b11 "
b11 =
1+
#800
0+
0&
#805
b1 C
1+
#810
0+
#815
b10 C
1+
#820
0+
#825
b11 C
1+
#830
0+
#835
b100 C
1+
#840
0+
#845
b10 "
b10 =
b11 !
b11 >
b10 @
b0 C
1+
#850
0+
#855
b1 C
1+
#860
0+
#865
b10 C
1+
#870
0+
#875
b11 C
1+
#880
0+
#885
b100 C
1+
#890
0+
#895
b1 "
b1 =
b10 !
b10 >
b0 C
1+
#900
0+
#905
b1 C
1+
#910
0+
#915
b10 C
1+
#920
0+
#925
b11 C
1+
#930
0+
#935
b100 C
1+
#940
0+
#945
b110 ?
b0 "
b0 =
b1 !
b1 >
b0 C
1+
#950
0+
b10 )
b10 /
#955
b1 C
1+
#960
0+
1%
#965
b10 C
1+
#970
0+
#975
b11 C
1+
#980
0+
0%
#985
b100 C
1+
#990
0+
#995
b1001 ?
b1 B
b0 C
1+
#1000
0+
#1005
b1 C
1+
#1010
0+
#1015
b10 C
1+
#1020
0+
#1025
b11 C
1+
#1030
0+
#1035
b100 C
1+
#1040
0+
#1045
b10 ?
b0 C
1+
#1050
0+
b10 '
b10 -
#1055
1+
#1060
0+
1%
#1065
b101 ?
b10 !
b10 >
1+
#1070
0+
0%
#1075
b1 C
1+
#1080
0+
#1085
b10 C
1+
#1090
0+
#1095
b11 C
1+
#1100
0+
#1105
b100 C
1+
#1110
0+
#1115
b1 "
b1 =
b1 !
b1 >
b0 C
1+
#1120
0+
#1125
b1 C
1+
#1130
0+
#1135
b10 C
1+
#1140
0+
#1145
b11 C
1+
#1150
0+
#1155
b100 C
1+
#1160
0+
#1165
b10 "
b10 =
b0 !
b0 >
b0 C
1+
#1170
0+
#1175
b1 C
1+
#1180
0+
#1185
b10 C
1+
#1190
0+
#1195
b11 C
1+
#1200
0+
#1205
b100 C
1+
#1210
0+
#1215
b11 "
b11 =
b1 !
b1 >
b1 @
b0 C
1+
#1220
0+
#1225
b1 C
1+
#1230
0+
#1235
b10 C
1+
#1240
0+
#1245
b11 C
1+
#1250
0+
#1255
b100 C
1+
#1260
0+
#1265
b111 ?
b100 "
b100 =
b10 !
b10 >
b0 C
1+
#1270
0+
#1275
b1 C
1+
#1280
0+
1&
#1285
b10 C
1+
#1290
0+
#1295
b11 C
1+
#1300
0+
0&
#1305
b100 C
1+
#1310
0+
#1315
b1000 ?
b10 A
b0 C
1+
#1320
0+
#1325
b1 C
1+
#1330
0+
#1335
b10 C
1+
#1340
0+
#1345
b11 C
1+
#1350
0+
#1355
b100 C
1+
#1360
0+
#1365
b11 ?
b0 C
1+
#1370
0+
b0 (
b0 .
#1375
1+
#1380
0+
1&
#1385
b100 ?
b0 @
b11 !
b11 >
1+
#1390
0+
0&
#1395
b1 C
1+
#1400
0+
#1405
b10 C
1+
#1410
0+
#1415
b11 C
1+
#1420
0+
#1425
b100 C
1+
#1430
0+
#1435
b11 "
b11 =
b0 C
1+
#1440
0+
#1445
b1 C
1+
#1450
0+
#1455
b10 C
1+
#1460
0+
#1465
b11 C
1+
#1470
0+
#1475
b100 C
1+
#1480
0+
#1485
b10 "
b10 =
b0 C
1+
#1490
0+
#1495
b1 C
1+
#1500
0+
#1505
b10 C
1+
#1510
0+
#1515
b11 C
1+
#1520
0+
#1525
b100 C
1+
#1530
0+
#1535
b1 "
b1 =
b0 C
1+
#1540
0+
#1545
b1 C
1+
#1550
0+
#1555
b10 C
1+
#1560
0+
#1565
b11 C
1+
#1570
0+
#1575
b100 C
1+
#1580
0+
#1585
b110 ?
b0 "
b0 =
b0 C
1+
#1590
0+
b11 )
b11 /
#1595
b1 C
1+
#1600
0+
1%
#1605
b101 ?
b10 !
b10 >
b10 @
b0 C
b1 "
b1 =
1+
#1610
0+
0%
#1615
b1 C
1+
#1620
0+
#1625
b10 C
1+
#1630
0+
#1635
b11 C
1+
#1640
0+
#1645
b100 C
1+
#1650
0+
#1655
b10 "
b10 =
b1 !
b1 >
b0 C
1+
#1660
0+
#1665
b1 C
1+
#1670
0+
#1675
b10 C
1+
#1680
0+
#1685
b11 C
1+
#1690
0+
#1695
b100 C
1+
#1700
0+
#1705
b11 "
b11 =
b0 !
b0 >
b0 C
1+
#1710
0+
#1715
b1 C
1+
#1720
0+
#1725
b10 C
1+
#1730
0+
#1735
b11 C
1+
#1740
0+
#1745
b100 C
1+
#1750
0+
#1755
b111 ?
b100 "
b100 =
b1 !
b1 >
b1 @
b0 C
1+
#1760
0+
b1 *
b1 0
#1765
b1 C
1+
#1770
0+
1&
#1775
b100 ?
b0 @
b0 C
b11 "
b11 =
1+
#1780
0+
0&
#1785
b1 C
1+
#1790
0+
#1795
b10 C
1+
#1800
0+
#1805
b11 C
1+
#1810
0+
#1815
b100 C
1+
#1820
0+
#1825
b10 "
b10 =
b0 C
1+
#1830
0+
#1835
b1 C
1+
#1840
0+
#1845
b10 C
1+
#1850
0+
#1855
b11 C
1+
#1860
0+
#1865
b100 C
1+
#1870
0+
#1875
b1 "
b1 =
b0 C
1+
#1880
0+
#1885
b1 C
1+
#1890
0+
#1895
b10 C
1+
#1900
0+
#1905
b11 C
1+
#1910
0+
#1915
b100 C
1+
#1920
0+
#1925
b110 ?
b0 "
b0 =
b0 C
1+
#1930
0+
b1 )
b1 /
#1935
b1 C
1+
#1940
0+
1%
#1945
b101 ?
b0 !
b0 >
b10 @
b0 C
b1 "
b1 =
1+
#1950
0+
0%
#1955
b1 C
1+
#1960
0+
#1965
b10 C
1+
#1970
0+
#1975
b11 C
1+
#1980
0+
#1985
b100 C
1+
#1990
0+
#1995
b10 "
b10 =
b1 !
b1 >
b1 @
b0 C
1+
#2000
0+
#2005
b1 C
1+
#2010
0+
#2015
b10 C
1+
#2020
0+
#2025
b11 C
1+
#2030
0+
#2035
b100 C
1+
#2040
0+
#2045
b11 "
b11 =
b10 !
b10 >
b0 C
1+
#2050
0+
#2055
b1 C
1+
#2060
0+
#2065
b10 C
1+
#2070
0+
#2075
b11 C
1+
#2080
0+
#2085
b100 C
1+
#2090
0+
#2095
b111 ?
b100 "
b100 =
b11 !
b11 >
b0 C
1+
#2100
0+
b0 *
b0 0
#2105
b1 C
1+
#2110
0+
1&
#2115
b10 C
1+
#2120
0+
#2125
b11 C
1+
#2130
0+
0&
#2135
b100 C
1+
#2140
0+
#2145
b1000 ?
b11 A
b0 C
1+
#2150
0+
#2155
b1 C
1+
#2160
0+
#2165
b10 C
1+
#2170
0+
#2175
b11 C
1+
#2180
0+
#2185
b100 C
1+
#2190
0+
#2195
b1010 ?
b0 C
1+
#2200
b0 ?
b0 !
b0 >
b0 "
b0 =
b0 B
b0 A
b0 @
0+
1,
b0 )
b0 /
b0 '
b0 -
#2205
1+
#2210
0+
0,
#2215
1+
#2220
0+
1&
#2225
b1 ?
1D
1+
#2230
0+
0&
#2235
b1 C
1+
#2240
0+
#2245
b10 C
1+
#2250
0+
#2255
b11 C
1+
#2260
0+
#2265
b100 C
1+
#2270
0+
b10 (
b10 .
b100 *
b100 0
#2275
b11 ?
b0 C
1+
#2280
0+
1&
#2285
b100 ?
b10 @
b100 !
b100 >
b100 "
b100 =
1+
#2290
0+
0&
#2295
b1 C
1+
#2300
0+
#2305
b10 C
1+
#2310
0+
#2315
b11 C
1+
#2320
0+
#2325
b100 C
1+
#2330
0+
#2335
b11 "
b11 =
b11 !
b11 >
b0 C
1+
#2340
0+
#2345
b1 C
1+
#2350
0+
#2355
b10 C
1+
#2360
0+
#2365
b11 C
1+
#2370
0+
#2375
b100 C
1+
#2380
0+
#2385
b10 "
b10 =
b10 !
b10 >
b0 C
1+
#2390
0+
#2395
b1 C
1+
#2400
0+
#2405
b10 C
1+
#2410
0+
#2415
b11 C
1+
#2420
0+
#2425
b100 C
1+
#2430
0+
